odoo/addons/sale_order_global_stock_route/README.rst
odoo/addons/sale_order_global_stock_route/__init__.py
odoo/addons/sale_order_global_stock_route/__manifest__.py
odoo/addons/sale_order_global_stock_route/i18n/es.po
odoo/addons/sale_order_global_stock_route/i18n/it.po
odoo/addons/sale_order_global_stock_route/i18n/pt_BR.po
odoo/addons/sale_order_global_stock_route/i18n/sale_order_global_stock_route.pot
odoo/addons/sale_order_global_stock_route/models/__init__.py
odoo/addons/sale_order_global_stock_route/models/sale_order.py
odoo/addons/sale_order_global_stock_route/readme/CONFIGURE.rst
odoo/addons/sale_order_global_stock_route/readme/CONTRIBUTORS.rst
odoo/addons/sale_order_global_stock_route/readme/DESCRIPTION.rst
odoo/addons/sale_order_global_stock_route/readme/USAGE.rst
odoo/addons/sale_order_global_stock_route/static/description/icon.png
odoo/addons/sale_order_global_stock_route/static/description/index.html
odoo/addons/sale_order_global_stock_route/tests/__init__.py
odoo/addons/sale_order_global_stock_route/tests/test_sale_order_global_stock_route.py
odoo/addons/sale_order_global_stock_route/views/sale_order_views.xml
odoo12_addon_sale_order_global_stock_route-12.0.1.0.2.dist-info/METADATA
odoo12_addon_sale_order_global_stock_route-12.0.1.0.2.dist-info/WHEEL
odoo12_addon_sale_order_global_stock_route-12.0.1.0.2.dist-info/top_level.txt
odoo12_addon_sale_order_global_stock_route-12.0.1.0.2.dist-info/RECORD
